odoo9_addon_account_financial_report_qweb-9.0.1.0.5-py2.7-nspkg.pth
odoo9_addon_account_financial_report_qweb-9.0.1.0.5.dist-info/METADATA
odoo9_addon_account_financial_report_qweb-9.0.1.0.5.dist-info/RECORD
odoo9_addon_account_financial_report_qweb-9.0.1.0.5.dist-info/WHEEL
odoo9_addon_account_financial_report_qweb-9.0.1.0.5.dist-info/namespace_packages.txt
odoo9_addon_account_financial_report_qweb-9.0.1.0.5.dist-info/top_level.txt
odoo_addons/account_financial_report_qweb/README.rst
odoo_addons/account_financial_report_qweb/__init__.py
odoo_addons/account_financial_report_qweb/__openerp__.py
odoo_addons/account_financial_report_qweb/menuitems.xml
odoo_addons/account_financial_report_qweb/reports.xml
odoo_addons/account_financial_report_qweb/i18n/account_financial_report_qweb.pot
odoo_addons/account_financial_report_qweb/i18n/ca.po
odoo_addons/account_financial_report_qweb/i18n/de.po
odoo_addons/account_financial_report_qweb/i18n/es.po
odoo_addons/account_financial_report_qweb/i18n/fr.po
odoo_addons/account_financial_report_qweb/i18n/pt.po
odoo_addons/account_financial_report_qweb/models/__init__.py
odoo_addons/account_financial_report_qweb/models/account.py
odoo_addons/account_financial_report_qweb/report/__init__.py
odoo_addons/account_financial_report_qweb/report/abstract_report.py
odoo_addons/account_financial_report_qweb/report/abstract_report_xlsx.py
odoo_addons/account_financial_report_qweb/report/aged_partner_balance.py
odoo_addons/account_financial_report_qweb/report/aged_partner_balance_xlsx.py
odoo_addons/account_financial_report_qweb/report/general_ledger.py
odoo_addons/account_financial_report_qweb/report/general_ledger_xlsx.py
odoo_addons/account_financial_report_qweb/report/open_items.py
odoo_addons/account_financial_report_qweb/report/open_items_xlsx.py
odoo_addons/account_financial_report_qweb/report/trial_balance.py
odoo_addons/account_financial_report_qweb/report/trial_balance_xlsx.py
odoo_addons/account_financial_report_qweb/report/templates/aged_partner_balance.xml
odoo_addons/account_financial_report_qweb/report/templates/general_ledger.xml
odoo_addons/account_financial_report_qweb/report/templates/layouts.xml
odoo_addons/account_financial_report_qweb/report/templates/open_items.xml
odoo_addons/account_financial_report_qweb/report/templates/trial_balance.xml
