Metadata-Version: 2.1
Name: odoo9-addon-account-financial-report-qweb
Version: 9.0.1.0.5
Summary: OCA Financial Reports
Home-page: https://odoo-community.org/
Author: Camptocamp SA,initOS GmbH,redCOR AG,Odoo Community Association (OCA)
Author-email: support@odoo-community.org
License: AGPL-3
Platform: UNKNOWN
Classifier: Programming Language :: Python
Classifier: Framework :: Odoo
Classifier: License :: OSI Approved :: GNU Affero General Public License v3
Requires-Python: ~=2.7
Requires-Dist: odoo9-addon-date-range
Requires-Dist: odoo9-addon-report-xlsx
Requires-Dist: odoo (<9.1a,>=9.0a)
